{
  "name": "丽贝卡",
  "attributeId": 3,
  "weaponTypeId": 3,
  "starLevel": 5,
  "stats": {
    "0": {
      "1": {
        "life": 928.0,
        "atk": 32.0,
        "def": 96.0
      },
      "2": {
        "life": 1006.1376,
        "atk": 34.6944,
        "def": 103.9008
      },
      "3": {
        "life": 1084.368,
        "atk": 37.392,
        "def": 111.8112
      },
      "4": {
        "life": 1162.5984,
        "atk": 40.0896,
        "def": 119.7216
      },
      "5": {
        "life": 1240.736,
        "atk": 42.784,
        "def": 127.632
      },
      "6": {
        "life": 1318.9664,
        "atk": 45.4816,
        "def": 135.5424
      },
      "7": {
        "life": 1397.1968,
        "atk": 48.1792,
        "def": 143.4528
      },
      "8": {
        "life": 1475.3344,
        "atk": 50.8736,
        "def": 151.3632
      },
      "9": {
        "life": 1553.5648,
        "atk": 53.5712,
        "def": 159.2736
      },
      "10": {
        "life": 1631.7952,
        "atk": 56.2688,
        "def": 167.184
      },
      "11": {
        "life": 1709.9328,
        "atk": 58.9632,
        "def": 175.0944
      },
      "12": {
        "life": 1788.1632,
        "atk": 61.6608,
        "def": 183.0048
      },
      "13": {
        "life": 1866.3936,
        "atk": 64.3584,
        "def": 190.9152
      },
      "14": {
        "life": 1944.624,
        "atk": 67.056,
        "def": 198.8256
      },
      "15": {
        "life": 2022.7616,
        "atk": 69.7504,
        "def": 206.736
      },
      "16": {
        "life": 2100.992,
        "atk": 72.448,
        "def": 214.6464
      },
      "17": {
        "life": 2179.2224,
        "atk": 75.1456,
        "def": 222.5568
      },
      "18": {
        "life": 2257.36,
        "atk": 77.84,
        "def": 230.4672
      },
      "19": {
        "life": 2335.5904,
        "atk": 80.5376,
        "def": 238.3776
      },
      "20": {
        "life": 2413.8208,
        "atk": 83.2352,
        "def": 246.288
      }
    },
    "1": {
      "20": {
        "life": 3032.4256,
        "atk": 107.2352,
        "def": 308.5056
      },
      "21": {
        "life": 3110.656,
        "atk": 109.9296,
        "def": 316.416
      },
      "22": {
        "life": 3188.8864,
        "atk": 112.6272,
        "def": 324.3264
      },
      "23": {
        "life": 3267.024,
        "atk": 115.3248,
        "def": 332.2368
      },
      "24": {
        "life": 3345.2544,
        "atk": 118.0224,
        "def": 340.1472
      },
      "25": {
        "life": 3423.4848,
        "atk": 120.7168,
        "def": 348.0576
      },
      "26": {
        "life": 3501.7152,
        "atk": 123.4144,
        "def": 355.968
      },
      "27": {
        "life": 3579.8528,
        "atk": 126.112,
        "def": 363.8784
      },
      "28": {
        "life": 3658.0832,
        "atk": 128.8064,
        "def": 371.7888
      },
      "29": {
        "life": 3736.3136,
        "atk": 131.504,
        "def": 379.6992
      },
      "30": {
        "life": 3814.4512,
        "atk": 134.2016,
        "def": 387.6096
      },
      "31": {
        "life": 3892.6816,
        "atk": 136.896,
        "def": 395.52
      },
      "32": {
        "life": 3970.912,
        "atk": 139.5936,
        "def": 403.4304
      },
      "33": {
        "life": 4049.0496,
        "atk": 142.2912,
        "def": 411.3408
      },
      "34": {
        "life": 4127.28,
        "atk": 144.9856,
        "def": 419.2512
      },
      "35": {
        "life": 4205.5104,
        "atk": 147.6832,
        "def": 427.1616
      },
      "36": {
        "life": 4283.7408,
        "atk": 150.3808,
        "def": 435.072
      },
      "37": {
        "life": 4361.8784,
        "atk": 153.0784,
        "def": 442.9824
      },
      "38": {
        "life": 4440.1088,
        "atk": 155.7728,
        "def": 450.8928
      },
      "39": {
        "life": 4518.3392,
        "atk": 158.4704,
        "def": 458.8032
      },
      "40": {
        "life": 4596.4768,
        "atk": 161.168,
        "def": 466.7136
      }
    },
    "2": {
      "40": {
        "life": 5215.1744,
        "atk": 185.168,
        "def": 528.9312
      },
      "41": {
        "life": 5293.4048,
        "atk": 187.8624,
        "def": 536.8416
      },
      "42": {
        "life": 5371.5424,
        "atk": 190.56,
        "def": 544.752
      },
      "43": {
        "life": 5449.7728,
        "atk": 193.2576,
        "def": 552.6624
      },
      "44": {
        "life": 5528.0032,
        "atk": 195.952,
        "def": 560.5728
      },
      "45": {
        "life": 5606.1408,
        "atk": 198.6496,
        "def": 568.4832
      },
      "46": {
        "life": 5684.3712,
        "atk": 201.3472,
        "def": 576.3936
      },
      "47": {
        "life": 5762.6016,
        "atk": 204.0448,
        "def": 584.304
      },
      "48": {
        "life": 5840.832,
        "atk": 206.7392,
        "def": 592.2144
      },
      "49": {
        "life": 5918.9696,
        "atk": 209.4368,
        "def": 600.1248
      },
      "50": {
        "life": 5997.2,
        "atk": 212.1344,
        "def": 608.0352
      }
    },
    "3": {
      "50": {
        "life": 6615.8976,
        "atk": 236.1344,
        "def": 670.2528
      },
      "51": {
        "life": 6694.0352,
        "atk": 238.8288,
        "def": 678.1632
      },
      "52": {
        "life": 6772.2656,
        "atk": 241.5264,
        "def": 686.0736
      },
      "53": {
        "life": 6850.496,
        "atk": 244.224,
        "def": 693.984
      },
      "54": {
        "life": 6928.6336,
        "atk": 246.9184,
        "def": 701.8944
      },
      "55": {
        "life": 7006.864,
        "atk": 249.616,
        "def": 709.8048
      },
      "56": {
        "life": 7085.0944,
        "atk": 252.3136,
        "def": 717.7152
      },
      "57": {
        "life": 7163.3248,
        "atk": 255.0112,
        "def": 725.6256
      },
      "58": {
        "life": 7241.4624,
        "atk": 257.7056,
        "def": 733.536
      },
      "59": {
        "life": 7319.6928,
        "atk": 260.4032,
        "def": 741.4464
      },
      "60": {
        "life": 7397.9232,
        "atk": 263.1008,
        "def": 749.3568
      }
    },
    "4": {
      "60": {
        "life": 8016.528,
        "atk": 287.1008,
        "def": 811.584
      },
      "61": {
        "life": 8094.7584,
        "atk": 289.7952,
        "def": 819.4944
      },
      "62": {
        "life": 8172.9888,
        "atk": 292.4928,
        "def": 827.4048
      },
      "63": {
        "life": 8251.1264,
        "atk": 295.1904,
        "def": 835.3152
      },
      "64": {
        "life": 8329.3568,
        "atk": 297.8848,
        "def": 843.2256
      },
      "65": {
        "life": 8407.5872,
        "atk": 300.5824,
        "def": 851.136
      },
      "66": {
        "life": 8485.7248,
        "atk": 303.28,
        "def": 859.0368
      },
      "67": {
        "life": 8563.9552,
        "atk": 305.9744,
        "def": 866.9472
      },
      "68": {
        "life": 8642.1856,
        "atk": 308.672,
        "def": 874.8576
      },
      "69": {
        "life": 8720.416,
        "atk": 311.3696,
        "def": 882.768
      },
      "70": {
        "life": 8798.5536,
        "atk": 314.0672,
        "def": 890.6784
      }
    },
    "5": {
      "70": {
        "life": 9417.2512,
        "atk": 330.0672,
        "def": 952.9056
      },
      "71": {
        "life": 9495.4816,
        "atk": 332.7616,
        "def": 960.816
      },
      "72": {
        "life": 9573.6192,
        "atk": 335.4592,
        "def": 968.7264
      },
      "73": {
        "life": 9651.8496,
        "atk": 338.1568,
        "def": 976.6368
      },
      "74": {
        "life": 9730.08,
        "atk": 340.8512,
        "def": 984.5472
      },
      "75": {
        "life": 9808.2176,
        "atk": 343.5488,
        "def": 992.4576
      },
      "76": {
        "life": 9886.448,
        "atk": 346.2464,
        "def": 1000.368
      },
      "77": {
        "life": 9964.6784,
        "atk": 348.9408,
        "def": 1008.2784
      },
      "78": {
        "life": 10042.816,
        "atk": 351.6384,
        "def": 1016.1888
      },
      "79": {
        "life": 10121.0464,
        "atk": 354.336,
        "def": 1024.0992
      },
      "80": {
        "life": 10199.2768,
        "atk": 357.0336,
        "def": 1032.0096
      }
    },
    "6": {
      "80": {
        "life": 10817.9744,
        "atk": 373.0336,
        "def": 1094.2272
      },
      "81": {
        "life": 10896.112,
        "atk": 375.728,
        "def": 1102.1376
      },
      "82": {
        "life": 10974.3424,
        "atk": 378.4256,
        "def": 1110.048
      },
      "83": {
        "life": 11052.5728,
        "atk": 381.1232,
        "def": 1117.9584
      },
      "84": {
        "life": 11130.7104,
        "atk": 383.8176,
        "def": 1125.8688
      },
      "85": {
        "life": 11208.9408,
        "atk": 386.5152,
        "def": 1133.7792
      },
      "86": {
        "life": 11287.1712,
        "atk": 389.2128,
        "def": 1141.6896
      },
      "87": {
        "life": 11365.3088,
        "atk": 391.9072,
        "def": 1149.6
      },
      "88": {
        "life": 11443.5392,
        "atk": 394.6048,
        "def": 1157.5104
      },
      "89": {
        "life": 11521.7696,
        "atk": 397.3024,
        "def": 1165.4208
      },
      "90": {
        "life": 11600.0,
        "atk": 400.0,
        "def": 1173.3312
      }
    }
  },
  "skillTree": {
    "1": {
      "skill": {
        "name": "混搭战术",
        "desc": "<color=Title>普攻·猎手</color>\n进行最多3段的攻击，造成<color=Thunder>导电伤害</color>。\n\n<color=Title>重击·猎手</color>\n<color=Highlight>长按普攻</color>，可持续对敌人进行射击，造成<color=Thunder>导电伤害</color>，此次伤害为普攻伤害。\n·若在长按过程中<color=Highlight>松开普攻</color>，且此时不处于施放<color=Highlight>战术闪避·猎手</color>期间，可以施放<color=Highlight>重击·吃枪子吧！·猎手</color>。\n\n<color=Title>重击·吃枪子吧！·猎手</color>\n造成<color=Thunder>导电伤害</color>。\n\n<color=Title>空中突袭！·猎手</color>\n从空中空翻落地。\n施放该技能后保持长按攻击可施放<color=Highlight>重击·猎手</color>。\n\n<color=Title>空中攻击·猎手</color>\n消耗耐力进行空中下落攻击，造成<color=Thunder>导电伤害</color>。\n\n<color=Title>闪避反击·猎手</color>\n成功闪避后一定时间内<color=Highlight>短按普攻</color>，将会攻击目标，造成<color=Thunder>导电伤害</color>。\n\n<color=Title>战术闪避·猎手</color>\n<color=Highlight>短按闪避</color>，闪避期间会攻击目标，造成<color=Thunder>导电伤害</color>。\n可以在进行以下操作时施放：\n·进行<color=Highlight>普攻·猎手</color>期间。\n·进行<color=Highlight>重击·猎手</color>期间。\n·施放<color=Highlight>空中突袭！·猎手</color>期间。\n·施放<color=Highlight>战术闪避·猎手</color>期间。\n·施放<color=Highlight>共鸣技能·有本事来抓我！</color>期间。\n·施放<color=Highlight>变奏技能·蠢货，有本事来抓我！</color>期间。\n使用<color=Highlight>战术闪避·猎手</color>成功闪避时，额外造成<color=Thunder>导电伤害</color>。\n\n<color=Title>普攻·铁胆</color>\n进行最多3段的攻击，造成<color=Thunder>导电伤害</color>。\n\n<color=Title>重击·铁胆</color>\n消耗耐力攻击目标，造成<color=Thunder>导电伤害</color>。\n\n<color=Title>空中攻击·铁胆</color>\n消耗耐力进行空中下落攻击，造成<color=Thunder>导电伤害</color>。\n\n<color=Title>闪避反击·铁胆</color>\n成功闪避后一定时间内<color=Highlight>短按普攻</color>，将会攻击目标，造成<color=Thunder>导电伤害</color>。\n\n<color=Title>战术闪避·铁胆</color>\n<color=Highlight>短按闪避</color>，闪避期间会攻击目标，造成<color=Thunder>导电伤害</color>。\n可以在进行以下操作时施放：\n·进行<color=Highlight>普攻·铁胆</color>期间。\n·施放<color=Highlight>战术闪避·铁胆</color>期间。\n·施放<color=Highlight>共鸣技能·来发大的！</color>期间。\n·施放<color=Highlight>变奏技能·呜呼，来发大的！</color>期间。\n使用<color=Highlight>战术闪避·铁胆</color>成功闪避时，额外造成<color=Thunder>导电伤害</color>。",
        "param": [],
        "type": "常态攻击",
        "level": {
          "1": {
            "name": "普攻·猎手第一段伤害",
            "param": [
              [
                "18.49%+18.49%",
                "20.01%+20.01%",
                "21.52%+21.52%",
                "23.65%+23.65%",
                "25.16%+25.16%",
                "26.91%+26.91%",
                "29.33%+29.33%",
                "31.76%+31.76%",
                "34.18%+34.18%",
                "36.76%+36.76%",
                "39.79%+39.79%",
                "42.82%+42.82%",
                "45.86%+45.86%",
                "48.89%+48.89%",
                "51.92%+51.92%",
                "54.95%+54.95%",
                "57.98%+57.98%",
                "61.02%+61.02%",
                "64.05%+64.05%",
                "67.08%+67.08%"
              ]
            ]
          },
          "2": {
            "name": "普攻·猎手第二段伤害",
            "param": [
              [
                "9.63%*4+9.63%",
                "10.42%*4+10.42%",
                "11.21%*4+11.21%",
                "12.31%*4+12.31%",
                "13.10%*4+13.10%",
                "14.01%*4+14.01%",
                "15.27%*4+15.27%",
                "16.53%*4+16.53%",
                "17.79%*4+17.79%",
                "19.13%*4+19.13%",
                "20.71%*4+20.71%",
                "22.29%*4+22.29%",
                "23.87%*4+23.87%",
                "25.45%*4+25.45%",
                "27.02%*4+27.02%",
                "28.60%*4+28.60%",
                "30.18%*4+30.18%",
                "31.76%*4+31.76%",
                "33.34%*4+33.34%",
                "34.91%*4+34.91%"
              ]
            ]
          },
          "3": {
            "name": "普攻·猎手第三段伤害",
            "param": [
              [
                "55.25%",
                "59.79%",
                "64.32%",
                "70.66%",
                "75.19%",
                "80.40%",
                "87.65%",
                "94.90%",
                "102.15%",
                "109.85%",
                "118.91%",
                "127.97%",
                "137.03%",
                "146.09%",
                "155.15%",
                "164.21%",
                "173.27%",
                "182.34%",
                "191.40%",
                "200.46%"
              ]
            ]
          },
          "4": {
            "name": "重击·猎手伤害",
            "param": [
              [
                "8.50%+8.50%",
                "9.20%+9.20%",
                "9.90%+9.90%",
                "10.87%+10.87%",
                "11.57%+11.57%",
                "12.37%+12.37%",
                "13.49%+13.49%",
                "14.60%+14.60%",
                "15.72%+15.72%",
                "16.90%+16.90%",
                "18.30%+18.30%",
                "19.69%+19.69%",
                "21.09%+21.09%",
                "22.48%+22.48%",
                "23.87%+23.87%",
                "25.27%+25.27%",
                "26.66%+26.66%",
                "28.06%+28.06%",
                "29.45%+29.45%",
                "30.84%+30.84%"
              ]
            ]
          },
          "5": {
            "name": "重击·吃枪子吧！·猎手",
            "param": [
              [
                "30.60%+30.60%",
                "33.11%+33.11%",
                "35.62%+35.62%",
                "39.14%+39.14%",
                "41.65%+41.65%",
                "44.53%+44.53%",
                "48.55%+48.55%",
                "52.56%+52.56%",
                "56.58%+56.58%",
                "60.84%+60.84%",
                "65.86%+65.86%",
                "70.88%+70.88%",
                "75.90%+75.90%",
                "80.91%+80.91%",
                "85.93%+85.93%",
                "90.95%+90.95%",
                "95.97%+95.97%",
                "100.99%+100.99%",
                "106.01%+106.01%",
                "111.02%+111.02%"
              ]
            ]
          },
          "6": {
            "name": "空中攻击·猎手伤害",
            "param": [
              [
                "68.43%",
                "74.04%",
                "79.65%",
                "87.51%",
                "93.12%",
                "99.57%",
                "108.55%",
                "117.52%",
                "126.50%",
                "136.04%",
                "147.26%",
                "158.48%",
                "169.71%",
                "180.93%",
                "192.15%",
                "203.37%",
                "214.59%",
                "225.81%",
                "237.04%",
                "248.26%"
              ]
            ]
          },
          "7": {
            "name": "闪避反击·猎手伤害",
            "param": [
              [
                "12.75%*4",
                "13.80%*4",
                "14.85%*4",
                "16.31%*4",
                "17.36%*4",
                "18.56%*4",
                "20.23%*4",
                "21.90%*4",
                "23.58%*4",
                "25.35%*4",
                "27.44%*4",
                "29.54%*4",
                "31.63%*4",
                "33.72%*4",
                "35.81%*4",
                "37.90%*4",
                "39.99%*4",
                "42.08%*4",
                "44.17%*4",
                "46.26%*4"
              ]
            ]
          },
          "8": {
            "name": "战术闪避·猎手伤害",
            "param": [
              [
                "8.50%+8.50%",
                "9.20%+9.20%",
                "9.90%+9.90%",
                "10.87%+10.87%",
                "11.57%+11.57%",
                "12.37%+12.37%",
                "13.49%+13.49%",
                "14.60%+14.60%",
                "15.72%+15.72%",
                "16.90%+16.90%",
                "18.30%+18.30%",
                "19.69%+19.69%",
                "21.09%+21.09%",
                "22.48%+22.48%",
                "23.87%+23.87%",
                "25.27%+25.27%",
                "26.66%+26.66%",
                "28.06%+28.06%",
                "29.45%+29.45%",
                "30.84%+30.84%"
              ]
            ]
          },
          "9": {
            "name": "战术闪避·猎手闪避成功伤害",
            "param": [
              [
                "74.80%",
                "80.94%",
                "87.07%",
                "95.66%",
                "101.79%",
                "108.85%",
                "118.66%",
                "128.47%",
                "138.29%",
                "148.71%",
                "160.98%",
                "173.25%",
                "185.52%",
                "197.78%",
                "210.05%",
                "222.32%",
                "234.59%",
                "246.85%",
                "259.12%",
                "271.39%"
              ]
            ]
          },
          "10": {
            "name": "普攻·铁胆第一段伤害",
            "param": [
              [
                "31.03%+31.03%",
                "33.57%+33.57%",
                "36.12%+36.12%",
                "39.68%+39.68%",
                "42.22%+42.22%",
                "45.15%+45.15%",
                "49.22%+49.22%",
                "53.29%+53.29%",
                "57.36%+57.36%",
                "61.69%+61.69%",
                "66.77%+66.77%",
                "71.86%+71.86%",
                "76.95%+76.95%",
                "82.04%+82.04%",
                "87.13%+87.13%",
                "92.21%+92.21%",
                "97.30%+97.30%",
                "102.39%+102.39%",
                "107.48%+107.48%",
                "112.57%+112.57%"
              ]
            ]
          },
          "11": {
            "name": "普攻·铁胆第二段伤害",
            "param": [
              [
                "42.50%",
                "45.99%",
                "49.47%",
                "54.35%",
                "57.84%",
                "61.85%",
                "67.42%",
                "73.00%",
                "78.57%",
                "84.50%",
                "91.47%",
                "98.44%",
                "105.41%",
                "112.38%",
                "119.35%",
                "126.32%",
                "133.29%",
                "140.26%",
                "147.23%",
                "154.20%"
              ]
            ]
          },
          "12": {
            "name": "普攻·铁胆第三段伤害",
            "param": [
              [
                "16.99%+16.99%+79.26%",
                "18.38%+18.38%+85.76%",
                "19.77%+19.77%+92.26%",
                "21.72%+21.72%+101.36%",
                "23.12%+23.12%+107.85%",
                "24.72%+24.72%+115.33%",
                "26.95%+26.95%+125.73%",
                "29.17%+29.17%+136.12%",
                "31.40%+31.40%+146.52%",
                "33.77%+33.77%+157.57%",
                "36.55%+36.55%+170.57%",
                "39.34%+39.34%+183.57%",
                "42.12%+42.12%+196.56%",
                "44.91%+44.91%+209.56%",
                "47.69%+47.69%+222.56%",
                "50.48%+50.48%+235.56%",
                "53.27%+53.27%+248.55%",
                "56.05%+56.05%+261.55%",
                "58.84%+58.84%+274.55%",
                "61.62%+61.62%+287.55%"
              ]
            ]
          },
          "13": {
            "name": "重击·铁胆伤害",
            "param": [
              [
                "102.00%",
                "110.37%",
                "118.73%",
                "130.44%",
                "138.81%",
                "148.43%",
                "161.81%",
                "175.19%",
                "188.57%",
                "202.79%",
                "219.52%",
                "236.25%",
                "252.98%",
                "269.70%",
                "286.43%",
                "303.16%",
                "319.89%",
                "336.62%",
                "353.34%",
                "370.07%"
              ]
            ]
          },
          "14": {
            "name": "空中攻击·铁胆伤害",
            "param": [
              [
                "52.70%",
                "57.03%",
                "61.35%",
                "67.40%",
                "71.72%",
                "76.69%",
                "83.60%",
                "90.52%",
                "97.43%",
                "104.78%",
                "113.42%",
                "122.06%",
                "130.71%",
                "139.35%",
                "147.99%",
                "156.63%",
                "165.28%",
                "173.92%",
                "182.56%",
                "191.21%"
              ]
            ]
          },
          "15": {
            "name": "闪避反击·铁胆伤害",
            "param": [
              [
                "51.00%",
                "55.19%",
                "59.37%",
                "65.22%",
                "69.41%",
                "74.22%",
                "80.91%",
                "87.60%",
                "94.29%",
                "101.40%",
                "109.76%",
                "118.13%",
                "126.49%",
                "134.85%",
                "143.22%",
                "151.58%",
                "159.95%",
                "168.31%",
                "176.67%",
                "185.04%"
              ]
            ]
          },
          "16": {
            "name": "战术闪避·铁胆伤害",
            "param": [
              [
                "31.03%",
                "33.57%",
                "36.12%",
                "39.68%",
                "42.22%",
                "45.15%",
                "49.22%",
                "53.29%",
                "57.36%",
                "61.69%",
                "66.77%",
                "71.86%",
                "76.95%",
                "82.04%",
                "87.13%",
                "92.21%",
                "97.30%",
                "102.39%",
                "107.48%",
                "112.57%"
              ]
            ]
          },
          "17": {
            "name": "战术闪避·铁胆闪避成功伤害",
            "param": [
              [
                "74.80%",
                "80.94%",
                "87.07%",
                "95.66%",
                "101.79%",
                "108.85%",
                "118.66%",
                "128.47%",
                "138.29%",
                "148.71%",
                "160.98%",
                "173.25%",
                "185.52%",
                "197.78%",
                "210.05%",
                "222.32%",
                "234.59%",
                "246.85%",
                "259.12%",
                "271.39%"
              ]
            ]
          },
          "18": {
            "name": "重击·猎手耐力消耗",
            "param": [
              [
                "20",
                "20",
                "20",
                "20",
                "20",
                "20",
                "20",
                "20",
                "20",
                "20",
                "20",
                "20",
                "20",
                "20",
                "20",
                "20",
                "20",
                "20",
                "20",
                "20"
              ]
            ]
          },
          "19": {
            "name": "空中攻击·猎手耐力消耗",
            "param": [
              [
                "30",
                "30",
                "30",
                "30",
                "30",
                "30",
                "30",
                "30",
                "30",
                "30",
                "30",
                "30",
                "30",
                "30",
                "30",
                "30",
                "30",
                "30",
                "30",
                "30"
              ]
            ]
          },
          "20": {
            "name": "战术闪避·猎手耐力消耗",
            "param": [
              [
                "20",
                "20",
                "20",
                "20",
                "20",
                "20",
                "20",
                "20",
                "20",
                "20",
                "20",
                "20",
                "20",
                "20",
                "20",
                "20",
                "20",
                "20",
                "20",
                "20"
              ]
            ]
          },
          "21": {
            "name": "重击·铁胆耐力消耗",
            "param": [
              [
                "20",
                "20",
                "20",
                "20",
                "20",
                "20",
                "20",
                "20",
                "20",
                "20",
                "20",
                "20",
                "20",
                "20",
                "20",
                "20",
                "20",
                "20",
                "20",
                "20"
              ]
            ]
          },
          "22": {
            "name": "空中攻击·铁胆耐力消耗",
            "param": [
              [
                "30",
                "30",
                "30",
                "30",
                "30",
                "30",
                "30",
                "30",
                "30",
                "30",
                "30",
                "30",
                "30",
                "30",
                "30",
                "30",
                "30",
                "30",
                "30",
                "30"
              ]
            ]
          },
          "23": {
            "name": "战术闪避·铁胆耐力消耗",
            "param": [
              [
                "20",
                "20",
                "20",
                "20",
                "20",
                "20",
                "20",
                "20",
                "20",
                "20",
                "20",
                "20",
                "20",
                "20",
                "20",
                "20",
                "20",
                "20",
                "20",
                "20"
              ]
            ]
          }
        },
        "consume": {
          "1": [],
          "2": [
            {
              "key": 43021021,
              "value": 2
            },
            {
              "key": 41100071,
              "value": 2
            },
            {
              "key": 2,
              "value": 1500
            }
          ],
          "3": [
            {
              "key": 43021021,
              "value": 3
            },
            {
              "key": 41100071,
              "value": 3
            },
            {
              "key": 2,
              "value": 2000
            }
          ],
          "4": [
            {
              "key": 43021022,
              "value": 2
            },
            {
              "key": 41100072,
              "value": 2
            },
            {
              "key": 2,
              "value": 4500
            }
          ],
          "5": [
            {
              "key": 43021022,
              "value": 3
            },
            {
              "key": 41100072,
              "value": 3
            },
            {
              "key": 2,
              "value": 6000
            }
          ],
          "6": [
            {
              "key": 43021023,
              "value": 3
            },
            {
              "key": 41100073,
              "value": 2
            },
            {
              "key": 2,
              "value": 16000
            }
          ],
          "7": [
            {
              "key": 43021023,
              "value": 5
            },
            {
              "key": 41100073,
              "value": 3
            },
            {
              "key": 41400304,
              "value": 1
            },
            {
              "key": 2,
              "value": 30000
            }
          ],
          "8": [
            {
              "key": 43021024,
              "value": 2
            },
            {
              "key": 41100074,
              "value": 2
            },
            {
              "key": 41400304,
              "value": 1
            },
            {
              "key": 2,
              "value": 50000
            }
          ],
          "9": [
            {
              "key": 43021024,
              "value": 3
            },
            {
              "key": 41100074,
              "value": 3
            },
            {
              "key": 41400304,
              "value": 1
            },
            {
              "key": 2,
              "value": 70000
            }
          ],
          "10": [
            {
              "key": 43021024,
              "value": 6
            },
            {
              "key": 41100074,
              "value": 4
            },
            {
              "key": 41400304,
              "value": 1
            },
            {
              "key": 2,
              "value": 100000
            }
          ]
        }
      }
    },
    "2": {
      "skill": {
        "name": "战术性调整",
        "desc": "<color=Title>共鸣技能·来发大的！</color>\n处于<color=Highlight>【猎手】</color>模式时，<color=Highlight>短按共鸣技能</color>，可接近敌人快速扫射，同时切换模式为<color=Highlight>【铁胆】</color>，并使用<color=Highlight>【铁胆】</color>轰击目标，造成<color=Thunder>导电伤害</color>。\n施放此技能后，一定时间内<color=Highlight>短按普攻</color>，可施放<color=Highlight>普攻·铁胆</color>第二段。\n\n<color=Title>共鸣技能·有本事来抓我！</color>\n处于<color=Highlight>【铁胆】</color>模式时，<color=Highlight>短按共鸣技能</color>，用<color=Highlight>【铁胆】</color>快速扫击敌人，然后对地射击利用后坐力接近敌人，同时切换模式为<color=Highlight>【猎手】</color>，并使用<color=Highlight>【猎手】</color>快速扫射，造成<color=Thunder>导电伤害</color>。\n施放该技能后，若处于低空，一定时内<color=Highlight>短按或长按普攻</color>可施放<color=Highlight>空中突袭！·猎手</color>。",
        "param": [],
        "type": "共鸣技能",
        "level": {
          "1": {
            "name": "共鸣技能·来发大的！伤害",
            "param": [
              [
                "11.90%+11.90%+11.90%+11.90%+17.85%+17.85%+17.85%+17.85%",
                "12.88%+12.88%+12.88%+12.88%+19.32%+19.32%+19.32%+19.32%",
                "13.86%+13.86%+13.86%+13.86%+20.78%+20.78%+20.78%+20.78%",
                "15.22%+15.22%+15.22%+15.22%+22.83%+22.83%+22.83%+22.83%",
                "16.20%+16.20%+16.20%+16.20%+24.30%+24.30%+24.30%+24.30%",
                "17.32%+17.32%+17.32%+17.32%+25.98%+25.98%+25.98%+25.98%",
                "18.88%+18.88%+18.88%+18.88%+28.32%+28.32%+28.32%+28.32%",
                "20.44%+20.44%+20.44%+20.44%+30.66%+30.66%+30.66%+30.66%",
                "22.00%+22.00%+22.00%+22.00%+33.00%+33.00%+33.00%+33.00%",
                "23.66%+23.66%+23.66%+23.66%+35.49%+35.49%+35.49%+35.49%",
                "25.61%+25.61%+25.61%+25.61%+38.42%+38.42%+38.42%+38.42%",
                "27.57%+27.57%+27.57%+27.57%+41.35%+41.35%+41.35%+41.35%",
                "29.52%+29.52%+29.52%+29.52%+44.27%+44.27%+44.27%+44.27%",
                "31.47%+31.47%+31.47%+31.47%+47.20%+47.20%+47.20%+47.20%",
                "33.42%+33.42%+33.42%+33.42%+50.13%+50.13%+50.13%+50.13%",
                "35.37%+35.37%+35.37%+35.37%+53.06%+53.06%+53.06%+53.06%",
                "37.32%+37.32%+37.32%+37.32%+55.98%+55.98%+55.98%+55.98%",
                "39.28%+39.28%+39.28%+39.28%+58.91%+58.91%+58.91%+58.91%",
                "41.23%+41.23%+41.23%+41.23%+61.84%+61.84%+61.84%+61.84%",
                "43.18%+43.18%+43.18%+43.18%+64.77%+64.77%+64.77%+64.77%"
              ]
            ]
          },
          "1-2": {
            "name": "骇破响应·熔触伤害",
            "param": [
              [
                "1186.50%",
                "1283.80%",
                "1381.09%",
                "1517.30%",
                "1614.59%",
                "1726.48%",
                "1882.15%",
                "2037.82%",
                "2193.49%",
                "2358.89%",
                "2553.47%",
                "2748.06%",
                "2942.64%",
                "3137.23%",
                "3331.82%",
                "3526.40%",
                "3720.99%",
                "3915.57%",
                "4110.16%",
                "4304.75%"
              ]
            ]
          },
          "2": {
            "name": "共鸣技能·有本事来抓我！伤害",
            "param": [
              [
                "11.90%+2.38%+11.90%+11.90%+69.02%+5.95%+5.95%",
                "12.88%+2.58%+12.88%+12.88%+74.68%+6.44%+6.44%",
                "13.86%+2.78%+13.86%+13.86%+80.34%+6.93%+6.93%",
                "15.22%+3.05%+15.22%+15.22%+88.27%+7.61%+7.61%",
                "16.20%+3.24%+16.20%+16.20%+93.93%+8.10%+8.10%",
                "17.32%+3.47%+17.32%+17.32%+100.44%+8.66%+8.66%",
                "18.88%+3.78%+18.88%+18.88%+109.49%+9.44%+9.44%",
                "20.44%+4.09%+20.44%+20.44%+118.55%+10.22%+10.22%",
                "22.00%+4.40%+22.00%+22.00%+127.60%+11.00%+11.00%",
                "23.66%+4.74%+23.66%+23.66%+137.22%+11.83%+11.83%",
                "25.61%+5.13%+25.61%+25.61%+148.54%+12.81%+12.81%",
                "27.57%+5.52%+27.57%+27.57%+159.86%+13.79%+13.79%",
                "29.52%+5.91%+29.52%+29.52%+171.18%+14.76%+14.76%",
                "31.47%+6.30%+31.47%+31.47%+182.50%+15.74%+15.74%",
                "33.42%+6.69%+33.42%+33.42%+193.82%+16.71%+16.71%",
                "35.37%+7.08%+35.37%+35.37%+205.14%+17.69%+17.69%",
                "37.32%+7.47%+37.32%+37.32%+216.46%+18.66%+18.66%",
                "39.28%+7.86%+39.28%+39.28%+227.78%+19.64%+19.64%",
                "41.23%+8.25%+41.23%+41.23%+239.10%+20.62%+20.62%",
                "43.18%+8.64%+43.18%+43.18%+250.42%+21.59%+21.59%"
              ]
            ]
          },
          "3": {
            "name": "共鸣技能·来发大的！冷却时间",
            "param": [
              [
                "1",
                "1",
                "1",
                "1",
                "1",
                "1",
                "1",
                "1",
                "1",
                "1",
                "1",
                "1",
                "1",
                "1",
                "1",
                "1",
                "1",
                "1",
                "1",
                "1"
              ]
            ]
          },
          "4": {
            "name": "共鸣技能·有本事来抓我！冷却时间",
            "param": [
              [
                "1",
                "1",
                "1",
                "1",
                "1",
                "1",
                "1",
                "1",
                "1",
                "1",
                "1",
                "1",
                "1",
                "1",
                "1",
                "1",
                "1",
                "1",
                "1",
                "1"
              ]
            ]
          }
        },
        "consume": {
          "1": [],
          "2": [
            {
              "key": 43021021,
              "value": 2
            },
            {
              "key": 41100071,
              "value": 2
            },
            {
              "key": 2,
              "value": 1500
            }
          ],
          "3": [
            {
              "key": 43021021,
              "value": 3
            },
            {
              "key": 41100071,
              "value": 3
            },
            {
              "key": 2,
              "value": 2000
            }
          ],
          "4": [
            {
              "key": 43021022,
              "value": 2
            },
            {
              "key": 41100072,
              "value": 2
            },
            {
              "key": 2,
              "value": 4500
            }
          ],
          "5": [
            {
              "key": 43021022,
              "value": 3
            },
            {
              "key": 41100072,
              "value": 3
            },
            {
              "key": 2,
              "value": 6000
            }
          ],
          "6": [
            {
              "key": 43021023,
              "value": 3
            },
            {
              "key": 41100073,
              "value": 2
            },
            {
              "key": 2,
              "value": 16000
            }
          ],
          "7": [
            {
              "key": 43021023,
              "value": 5
            },
            {
              "key": 41100073,
              "value": 3
            },
            {
              "key": 41400304,
              "value": 1
            },
            {
              "key": 2,
              "value": 30000
            }
          ],
          "8": [
            {
              "key": 43021024,
              "value": 2
            },
            {
              "key": 41100074,
              "value": 2
            },
            {
              "key": 41400304,
              "value": 1
            },
            {
              "key": 2,
              "value": 50000
            }
          ],
          "9": [
            {
              "key": 43021024,
              "value": 3
            },
            {
              "key": 41100074,
              "value": 3
            },
            {
              "key": 41400304,
              "value": 1
            },
            {
              "key": 2,
              "value": 70000
            }
          ],
          "10": [
            {
              "key": 43021024,
              "value": 6
            },
            {
              "key": 41100074,
              "value": 4
            },
            {
              "key": 41400304,
              "value": 1
            },
            {
              "key": 2,
              "value": 100000
            }
          ]
        }
      }
    },
    "3": {
      "skill": {
        "name": "狂欢时间！",
        "desc": "切换为<color=Highlight>【{0}型重机枪】</color>模式，生成停滞领域，{1}秒内：\n丽贝卡使用<color=Highlight>【{2}型重机枪】</color>自动射击，造成<color=Thunder>导电伤害</color>，并持续获得<color=Highlight>【过载】</color>。射击期间，一定时间后<color=Highlight>短按普攻</color>或<color=Highlight>共鸣解放</color>，可提升<color=Highlight>【{3}型重机枪】</color>威力，并更快的获得<color=Highlight>【过载】</color>，至多可触发2次。\n·机枪会自动锁定屏幕中央瞄准框内距离准星最近的敌人，不会攻击瞄准框外的敌人。\n·丽贝卡使用<color=Highlight>【{4}型重机枪】</color>期间无法移动，但获得{5}减伤和免疫打断。\n\n<color=Title>【过载】获取规则</color>\n<color=Highlight>【过载】</color>上限为{6}点。\n<color=Highlight>【{7}型重机枪】</color>未提升威力时：命中获得{8}点。\n<color=Highlight>【{9}型重机枪】</color>威力提升1次后：命中获得{10}点。\n<color=Highlight>【{11}型重机枪】</color>威力提升2次后：命中获得{12}点。\n\n<color=Title>大烟花！</color>\n<color=Highlight>【{13}型重机枪】</color>模式持续时间结束时或<color=Highlight>【过载】</color>达到上限时，自动施放<color=Highlight>大烟花！</color>，造成<color=Thunder>导电伤害</color>。施放<color=Highlight>大烟花！</color>时，会结束机枪状态。\n·<color=Highlight>【{14}型重机枪】</color>模式下<color=Highlight>长按共鸣解放</color>，可提前施放<color=Highlight>大烟花！</color>。",
        "param": [
          "31",
          "9",
          "31",
          "31",
          "31",
          "50%",
          "90",
          "31",
          "2",
          "31",
          "4",
          "31",
          "6",
          "31",
          "31"
        ],
        "type": "共鸣解放",
        "level": {
          "1": {
            "name": "大烟花！伤害",
            "param": [
              [
                "32.00%+288.00%",
                "34.63%+311.62%",
                "37.25%+335.24%",
                "40.93%+368.30%",
                "43.55%+391.92%",
                "46.57%+419.07%",
                "50.77%+456.86%",
                "54.96%+494.64%",
                "59.16%+532.43%",
                "63.62%+572.58%",
                "68.87%+619.81%",
                "74.12%+667.04%",
                "79.37%+714.27%",
                "84.62%+761.51%",
                "89.86%+808.74%",
                "95.11%+855.97%",
                "100.36%+903.20%",
                "105.61%+950.43%",
                "110.86%+997.67%",
                "116.10%+1044.90%"
              ]
            ]
          },
          "2": {
            "name": "冷却时间",
            "param": [
              [
                "25",
                "25",
                "25",
                "25",
                "25",
                "25",
                "25",
                "25",
                "25",
                "25",
                "25",
                "25",
                "25",
                "25",
                "25",
                "25",
                "25",
                "25",
                "25",
                "25"
              ]
            ]
          },
          "3": {
            "name": "【31型重机枪】伤害",
            "param": [
              [
                "13.34%*5",
                "14.43%*5",
                "15.52%*5",
                "17.06%*5",
                "18.15%*5",
                "19.41%*5",
                "21.16%*5",
                "22.90%*5",
                "24.65%*5",
                "26.51%*5",
                "28.70%*5",
                "30.89%*5",
                "33.07%*5",
                "35.26%*5",
                "37.45%*5",
                "39.63%*5",
                "41.82%*5",
                "44.01%*5",
                "46.19%*5",
                "48.38%*5"
              ]
            ]
          },
          "3-2": {
            "name": "消耗共鸣能量",
            "param": [
              [
                "125",
                "125",
                "125",
                "125",
                "125",
                "125",
                "125",
                "125",
                "125",
                "125",
                "125",
                "125",
                "125",
                "125",
                "125",
                "125",
                "125",
                "125",
                "125",
                "125"
              ]
            ]
          },
          "4": {
            "name": "回复协奏能量",
            "param": [
              [
                "20",
                "20",
                "20",
                "20",
                "20",
                "20",
                "20",
                "20",
                "20",
                "20",
                "20",
                "20",
                "20",
                "20",
                "20",
                "20",
                "20",
                "20",
                "20",
                "20"
              ]
            ]
          }
        },
        "consume": {
          "1": [],
          "2": [
            {
              "key": 43021021,
              "value": 2
            },
            {
              "key": 41100071,
              "value": 2
            },
            {
              "key": 2,
              "value": 1500
            }
          ],
          "3": [
            {
              "key": 43021021,
              "value": 3
            },
            {
              "key": 41100071,
              "value": 3
            },
            {
              "key": 2,
              "value": 2000
            }
          ],
          "4": [
            {
              "key": 43021022,
              "value": 2
            },
            {
              "key": 41100072,
              "value": 2
            },
            {
              "key": 2,
              "value": 4500
            }
          ],
          "5": [
            {
              "key": 43021022,
              "value": 3
            },
            {
              "key": 41100072,
              "value": 3
            },
            {
              "key": 2,
              "value": 6000
            }
          ],
          "6": [
            {
              "key": 43021023,
              "value": 3
            },
            {
              "key": 41100073,
              "value": 2
            },
            {
              "key": 2,
              "value": 16000
            }
          ],
          "7": [
            {
              "key": 43021023,
              "value": 5
            },
            {
              "key": 41100073,
              "value": 3
            },
            {
              "key": 41400304,
              "value": 1
            },
            {
              "key": 2,
              "value": 30000
            }
          ],
          "8": [
            {
              "key": 43021024,
              "value": 2
            },
            {
              "key": 41100074,
              "value": 2
            },
            {
              "key": 41400304,
              "value": 1
            },
            {
              "key": 2,
              "value": 50000
            }
          ],
          "9": [
            {
              "key": 43021024,
              "value": 3
            },
            {
              "key": 41100074,
              "value": 3
            },
            {
              "key": 41400304,
              "value": 1
            },
            {
              "key": 2,
              "value": 70000
            }
          ],
          "10": [
            {
              "key": 43021024,
              "value": 6
            },
            {
              "key": 41100074,
              "value": 4
            },
            {
              "key": 41400304,
              "value": 1
            },
            {
              "key": 2,
              "value": 100000
            }
          ]
        }
      }
    },
    "4": {
      "skill": {
        "name": "该你了！",
        "desc": "每次获得<color=Highlight>小孩子才做选择！</color>效果或者施放<color=Highlight>共鸣解放·狂欢时间！</color>时，攻击提升{0}，持续{1}秒，可叠加{2}层。队伍中角色的附加<color=Highlight>【骇破·偏移】</color>时，谐度破坏增幅提升{3}点，持续{4}秒。",
        "param": [
          "10%",
          "12",
          "2",
          "30",
          "30"
        ],
        "type": "固有技能",
        "level": {},
        "consume": {
          "1": [
            {
              "key": 43021022,
              "value": 3
            },
            {
              "key": 41100072,
              "value": 3
            },
            {
              "key": 41400304,
              "value": 1
            },
            {
              "key": 2,
              "value": 10000
            }
          ]
        }
      }
    },
    "5": {
      "skill": {
        "name": "有破绽！",
        "desc": "<color=Highlight>哒哒哒！·猎手</color>和<color=Highlight>砰砰砰！·铁胆</color>抗打断能力提升。\n瑞贝卡施放<color=Highlight>共鸣解放·狂欢时间！</color>时，附近队伍中所有角色攻击提升{0}，持续{1}秒。",
        "param": [
          "20%",
          "30"
        ],
        "type": "固有技能",
        "level": {},
        "consume": {
          "1": [
            {
              "key": 43021023,
              "value": 3
            },
            {
              "key": 41100073,
              "value": 3
            },
            {
              "key": 41400304,
              "value": 1
            },
            {
              "key": 2,
              "value": 20000
            }
          ]
        }
      }
    },
    "6": {
      "skill": {
        "name": "到我了！",
        "desc": "<color=Title>呜呼，来发大的！</color>\n处于<color=Highlight>【猎手】</color>模式时，变奏入场，接近敌人快速扫射，同时切换为<color=Highlight>【铁胆】</color>模式轰击目标，造成<color=Thunder>导电伤害</color>。\n施放此技能后，一定时间内<color=Highlight>短按普攻</color>，可施放<color=Highlight>普攻·铁胆</color>第二段。\n\n<color=Title>蠢货，有本事来抓我！</color>\n处于<color=Highlight>【铁胆】</color>模式时，变奏入场，对地射击利用后坐力接近敌人，同时切换为<color=Highlight>【猎手】</color>模式快速扫射，造成<color=Thunder>导电伤害</color>。\n施放该技能后，若处于低空，一定时间内<color=Highlight>短按或长按普攻</color>可施放<color=Highlight>空中突袭！·猎手</color>。",
        "param": [],
        "type": "变奏技能",
        "level": {
          "1": {
            "name": "呜呼，来发大的！伤害",
            "param": [
              [
                "13.60%+13.60%+13.60%+13.60%+13.60%+13.60%+20.40%+34.00%",
                "14.72%+14.72%+14.72%+14.72%+14.72%+14.72%+22.08%+36.79%",
                "15.84%+15.84%+15.84%+15.84%+15.84%+15.84%+23.75%+39.58%",
                "17.40%+17.40%+17.40%+17.40%+17.40%+17.40%+26.09%+43.48%",
                "18.51%+18.51%+18.51%+18.51%+18.51%+18.51%+27.77%+46.27%",
                "19.79%+19.79%+19.79%+19.79%+19.79%+19.79%+29.69%+49.48%",
                "21.58%+21.58%+21.58%+21.58%+21.58%+21.58%+32.37%+53.94%",
                "23.36%+23.36%+23.36%+23.36%+23.36%+23.36%+35.04%+58.40%",
                "25.15%+25.15%+25.15%+25.15%+25.15%+25.15%+37.72%+62.86%",
                "27.04%+27.04%+27.04%+27.04%+27.04%+27.04%+40.56%+67.60%",
                "29.27%+29.27%+29.27%+29.27%+29.27%+29.27%+43.91%+73.18%",
                "31.50%+31.50%+31.50%+31.50%+31.50%+31.50%+47.25%+78.75%",
                "33.73%+33.73%+33.73%+33.73%+33.73%+33.73%+50.60%+84.33%",
                "35.96%+35.96%+35.96%+35.96%+35.96%+35.96%+53.94%+89.90%",
                "38.20%+38.20%+38.20%+38.20%+38.20%+38.20%+57.29%+95.48%",
                "40.43%+40.43%+40.43%+40.43%+40.43%+40.43%+60.64%+101.06%",
                "42.66%+42.66%+42.66%+42.66%+42.66%+42.66%+63.98%+106.63%",
                "44.89%+44.89%+44.89%+44.89%+44.89%+44.89%+67.33%+112.21%",
                "47.12%+47.12%+47.12%+47.12%+47.12%+47.12%+70.67%+117.78%",
                "49.35%+49.35%+49.35%+49.35%+49.35%+49.35%+74.02%+123.36%"
              ]
            ]
          },
          "2": {
            "name": "蠢货，有本事来抓我！伤害",
            "param": [
              [
                "5.10%+15.30%+20.40%+20.40%+20.40%+20.40%",
                "5.52%+16.56%+22.08%+22.08%+22.08%+22.08%",
                "5.94%+17.81%+23.75%+23.75%+23.75%+23.75%",
                "6.53%+19.57%+26.09%+26.09%+26.09%+26.09%",
                "6.95%+20.83%+27.77%+27.77%+27.77%+27.77%",
                "7.43%+22.27%+29.69%+29.69%+29.69%+29.69%",
                "8.10%+24.28%+32.37%+32.37%+32.37%+32.37%",
                "8.76%+26.28%+35.04%+35.04%+35.04%+35.04%",
                "9.43%+28.29%+37.72%+37.72%+37.72%+37.72%",
                "10.14%+30.42%+40.56%+40.56%+40.56%+40.56%",
                "10.98%+32.93%+43.91%+43.91%+43.91%+43.91%",
                "11.82%+35.44%+47.25%+47.25%+47.25%+47.25%",
                "12.65%+37.95%+50.60%+50.60%+50.60%+50.60%",
                "13.49%+40.46%+53.94%+53.94%+53.94%+53.94%",
                "14.33%+42.97%+57.29%+57.29%+57.29%+57.29%",
                "15.16%+45.48%+60.64%+60.64%+60.64%+60.64%",
                "16.00%+47.99%+63.98%+63.98%+63.98%+63.98%",
                "16.84%+50.50%+67.33%+67.33%+67.33%+67.33%",
                "17.67%+53.01%+70.67%+70.67%+70.67%+70.67%",
                "18.51%+55.51%+74.02%+74.02%+74.02%+74.02%"
              ]
            ]
          },
          "3": {
            "name": "呜呼，来发大的！回复协奏能量",
            "param": [
              [
                "10",
                "10",
                "10",
                "10",
                "10",
                "10",
                "10",
                "10",
                "10",
                "10",
                "10",
                "10",
                "10",
                "10",
                "10",
                "10",
                "10",
                "10",
                "10",
                "10"
              ]
            ]
          },
          "4": {
            "name": "蠢货，有本事来抓我！回复协奏能量",
            "param": [
              [
                "10",
                "10",
                "10",
                "10",
                "10",
                "10",
                "10",
                "10",
                "10",
                "10",
                "10",
                "10",
                "10",
                "10",
                "10",
                "10",
                "10",
                "10",
                "10",
                "10"
              ]
            ]
          }
        },
        "consume": {
          "1": [],
          "2": [
            {
              "key": 43021021,
              "value": 2
            },
            {
              "key": 41100071,
              "value": 2
            },
            {
              "key": 2,
              "value": 1500
            }
          ],
          "3": [
            {
              "key": 43021021,
              "value": 3
            },
            {
              "key": 41100071,
              "value": 3
            },
            {
              "key": 2,
              "value": 2000
            }
          ],
          "4": [
            {
              "key": 43021022,
              "value": 2
            },
            {
              "key": 41100072,
              "value": 2
            },
            {
              "key": 2,
              "value": 4500
            }
          ],
          "5": [
            {
              "key": 43021022,
              "value": 3
            },
            {
              "key": 41100072,
              "value": 3
            },
            {
              "key": 2,
              "value": 6000
            }
          ],
          "6": [
            {
              "key": 43021023,
              "value": 3
            },
            {
              "key": 41100073,
              "value": 2
            },
            {
              "key": 2,
              "value": 16000
            }
          ],
          "7": [
            {
              "key": 43021023,
              "value": 5
            },
            {
              "key": 41100073,
              "value": 3
            },
            {
              "key": 41400304,
              "value": 1
            },
            {
              "key": 2,
              "value": 30000
            }
          ],
          "8": [
            {
              "key": 43021024,
              "value": 2
            },
            {
              "key": 41100074,
              "value": 2
            },
            {
              "key": 41400304,
              "value": 1
            },
            {
              "key": 2,
              "value": 50000
            }
          ],
          "9": [
            {
              "key": 43021024,
              "value": 3
            },
            {
              "key": 41100074,
              "value": 3
            },
            {
              "key": 41400304,
              "value": 1
            },
            {
              "key": 2,
              "value": 70000
            }
          ],
          "10": [
            {
              "key": 43021024,
              "value": 6
            },
            {
              "key": 41100074,
              "value": 4
            },
            {
              "key": 41400304,
              "value": 1
            },
            {
              "key": 2,
              "value": 100000
            }
          ]
        }
      }
    },
    "7": {
      "skill": {
        "name": "我要认真了！",
        "desc": "<color=Title>该用这个了！</color>\n丽贝卡施放<color=Highlight>共鸣技能</color>或<color=Highlight>变奏技能</color>可以在<color=Highlight>【猎手】</color>、<color=Highlight>【铁胆】</color>模式之间切换：\n·处于<color=Highlight>【猎手】</color>模式时，丽贝卡暴击伤害提升{0}。\n·处于<color=Highlight>【铁胆】</color>模式时，丽贝卡攻击无视目标{1}防御。\n·丽贝卡初始处于<color=Highlight>【猎手】</color>模式。\n\n<color=Title>骇破·偏移</color>\n瑞贝卡施放<color=Highlight>变奏技能·呜呼，来发大的！</color>、<color=Highlight>变奏技能·蠢货，有本事来抓我！</color>、<color=Highlight>哒哒哒！·猎手</color>、<color=Highlight>砰砰砰！·铁胆</color>、<color=Highlight>共鸣解放·大烟花！</color>造成伤害时会对目标附加<color=Highlight>【骇破·偏移】</color>，上述效果均每3秒可触发1次。\n\n<color=Title>骇破响应·熔触</color>\n丽贝卡对范围内处于<color=Highlight>【骇破·干涉】</color>状态的目标造成<color=Thunder>导电伤害</color>，此次伤害为骇破伤害。\n\n<color=Title>哒哒哒！·猎手</color>\n<color=Highlight>【狂热】</color>达到{2}点时，<color=Highlight>重击·猎手</color>替换为哒哒哒·猎手。<color=Highlight>长按普攻</color>施放<color=Highlight>哒哒哒！·猎手</color>，消耗所有的<color=Highlight>【狂热】</color>，造成<color=Thunder>导电伤害</color>，此次伤害为普攻伤害。\n在施放<color=Highlight>重击·猎手</color>期间，若<color=Highlight>【狂热】</color>达到{3}点，且此时不处于施放<color=Highlight>战术闪避·猎手</color>期间，可以通过<color=Highlight>松开普攻</color>施放<color=Highlight>哒哒哒！·猎手</color>。\n\n<color=Title>砰砰砰！·铁胆</color>\n<color=Highlight>【狂热】</color>达到{4}点时，<color=Highlight>重击·铁胆</color>替换为砰砰砰！·猎手。<color=Highlight>长按普攻</color>施放<color=Highlight>砰砰砰！·铁胆</color>，消耗所有的<color=Highlight>【狂热】</color>，造成<color=Thunder>导电伤害</color>，此次伤害为普攻伤害。\n\n<color=Title>【狂热】获取规则</color>\n<color=Highlight>【狂热】</color>上限{5}点。\n<color=Highlight>常态攻击</color>造成伤害时，回复<color=Highlight>【狂热】</color>。\n<color=Highlight>共鸣技能</color>造成伤害时，回复<color=Highlight>【狂热】</color>。\n施放<color=Highlight>变奏技能·呜呼，来发大的！</color>、<color=Highlight>变奏技能·蠢货，有本事来抓我！</color>时，回复{6}点狂热。\n\n<color=Title>【手感火热】获取规则</color>\n<color=Highlight>【手感火热】</color>上限{7}点。\n随时间持续获得，每秒获得{8}点。\n施放<color=Highlight>哒哒哒！·猎手</color>或<color=Highlight>砰砰砰！·铁胆</color>时回复{9}点。\n\n<color=Title>小孩子才做选择！</color>\n<color=Highlight>【手感火热】</color>达到{10}点时，施放<color=Highlight>变奏技能·呜呼，来发大的！</color>、<color=Highlight>变奏技能·蠢货，有本事来抓我！</color><color=Highlight>共鸣技能·来发大的！</color>或<color=Highlight>共鸣技能·有本事来抓我！</color>时，获得额外效果，{11}秒内：\n无论处于哪种模式，瑞贝卡同时获得<color=Highlight>【猎手】</color>和<color=Highlight>【铁胆】</color>模式的属性加成效果。\n此期间无法回复<color=Highlight>【手感火热】</color>，并且每秒消耗{12}点<color=Highlight>【手感火热】</color>。",
        "param": [
          "30%",
          "15%",
          "120",
          "120",
          "120",
          "120",
          "50",
          "120",
          "5",
          "40",
          "120",
          "12",
          "10"
        ],
        "type": "共鸣回路",
        "level": {
          "2": {
            "name": "哒哒哒！·猎手伤害",
            "param": [
              [
                "10.00%+10.00%+10.00%+160.00%+10.00%",
                "10.82%+10.82%+10.82%+173.12%+10.82%",
                "11.64%+11.64%+11.64%+186.24%+11.64%",
                "12.79%+12.79%+12.79%+204.61%+12.79%",
                "13.61%+13.61%+13.61%+217.73%+13.61%",
                "14.56%+14.56%+14.56%+232.82%+14.56%",
                "15.87%+15.87%+15.87%+253.81%+15.87%",
                "17.18%+17.18%+17.18%+274.80%+17.18%",
                "18.49%+18.49%+18.49%+295.80%+18.49%",
                "19.89%+19.89%+19.89%+318.10%+19.89%",
                "21.53%+21.53%+21.53%+344.34%+21.53%",
                "23.17%+23.17%+23.17%+370.58%+23.17%",
                "24.81%+24.81%+24.81%+396.82%+24.81%",
                "26.45%+26.45%+26.45%+423.06%+26.45%",
                "28.09%+28.09%+28.09%+449.30%+28.09%",
                "29.73%+29.73%+29.73%+475.54%+29.73%",
                "31.37%+31.37%+31.37%+501.78%+31.37%",
                "33.01%+33.01%+33.01%+528.02%+33.01%",
                "34.65%+34.65%+34.65%+554.26%+34.65%",
                "36.29%+36.29%+36.29%+580.50%+36.29%"
              ]
            ]
          },
          "3": {
            "name": "砰砰砰！·铁胆伤害",
            "param": [
              [
                "140.00%",
                "151.48%",
                "162.96%",
                "179.04%",
                "190.52%",
                "203.72%",
                "222.09%",
                "240.45%",
                "258.82%",
                "278.34%",
                "301.30%",
                "324.26%",
                "347.22%",
                "370.18%",
                "393.14%",
                "416.10%",
                "439.06%",
                "462.02%",
                "484.98%",
                "507.94%"
              ]
            ]
          },
          "4": {
            "name": "【31型重机枪】威力提升1次伤害",
            "param": [
              [
                "26.67%*5",
                "28.86%*5",
                "31.04%*5",
                "34.11%*5",
                "36.29%*5",
                "38.81%*5",
                "42.31%*5",
                "45.80%*5",
                "49.30%*5",
                "53.02%*5",
                "57.39%*5",
                "61.77%*5",
                "66.14%*5",
                "70.51%*5",
                "74.89%*5",
                "79.26%*5",
                "83.63%*5",
                "88.01%*5",
                "92.38%*5",
                "96.75%*5"
              ]
            ]
          },
          "5": {
            "name": "【31型重机枪】威力提升2次伤害",
            "param": [
              [
                "40.00%*10",
                "43.28%*10",
                "46.56%*10",
                "51.16%*10",
                "54.44%*10",
                "58.21%*10",
                "63.46%*10",
                "68.70%*10",
                "73.95%*10",
                "79.53%*10",
                "86.09%*10",
                "92.65%*10",
                "99.21%*10",
                "105.77%*10",
                "112.33%*10",
                "118.89%*10",
                "125.45%*10",
                "132.01%*10",
                "138.57%*10",
                "145.13%*10"
              ]
            ]
          }
        },
        "consume": {
          "1": [],
          "2": [
            {
              "key": 43021021,
              "value": 2
            },
            {
              "key": 41100071,
              "value": 2
            },
            {
              "key": 2,
              "value": 1500
            }
          ],
          "3": [
            {
              "key": 43021021,
              "value": 3
            },
            {
              "key": 41100071,
              "value": 3
            },
            {
              "key": 2,
              "value": 2000
            }
          ],
          "4": [
            {
              "key": 43021022,
              "value": 2
            },
            {
              "key": 41100072,
              "value": 2
            },
            {
              "key": 2,
              "value": 4500
            }
          ],
          "5": [
            {
              "key": 43021022,
              "value": 3
            },
            {
              "key": 41100072,
              "value": 3
            },
            {
              "key": 2,
              "value": 6000
            }
          ],
          "6": [
            {
              "key": 43021023,
              "value": 3
            },
            {
              "key": 41100073,
              "value": 2
            },
            {
              "key": 2,
              "value": 16000
            }
          ],
          "7": [
            {
              "key": 43021023,
              "value": 5
            },
            {
              "key": 41100073,
              "value": 3
            },
            {
              "key": 41400304,
              "value": 1
            },
            {
              "key": 2,
              "value": 30000
            }
          ],
          "8": [
            {
              "key": 43021024,
              "value": 2
            },
            {
              "key": 41100074,
              "value": 2
            },
            {
              "key": 41400304,
              "value": 1
            },
            {
              "key": 2,
              "value": 50000
            }
          ],
          "9": [
            {
              "key": 43021024,
              "value": 3
            },
            {
              "key": 41100074,
              "value": 3
            },
            {
              "key": 41400304,
              "value": 1
            },
            {
              "key": 2,
              "value": 70000
            }
          ],
          "10": [
            {
              "key": 43021024,
              "value": 6
            },
            {
              "key": 41100074,
              "value": 4
            },
            {
              "key": 41400304,
              "value": 1
            },
            {
              "key": 2,
              "value": 100000
            }
          ]
        }
      }
    },
    "8": {
      "skill": {
        "name": "好搭档",
        "desc": "召唤机枪塔持续攻击敌人，持续{0}秒，造成<color=Thunder>导电伤害</color>。\n下一位登场角色获得<color=Highlight>浪客羁绊</color>，全伤害加深{1}，持续{2}秒。机枪每次攻击时，持有<color=Highlight>浪客羁绊</color>的角色会获得{3}层<color=Highlight>超限</color>，造成重击伤害加深{4}（若是露西持有<color=Highlight>浪客羁绊</color>，则直接获得满层），可叠加{5}层。若切换至其他角色则提前结束<color=Highlight>浪客羁绊</color>和<color=Highlight>超限</color>。\n机枪塔可被露西强化，伤害倍率提升{6}，但持续时间变为{7}秒。",
        "param": [
          "14",
          "15%",
          "14",
          "1",
          "0.5%",
          "70",
          "250%",
          "4"
        ],
        "type": "延奏技能",
        "level": {},
        "consume": {
          "1": []
        }
      }
    },
    "9": {
      "skill": {
        "name": "暴击提升",
        "desc": "暴击提升{0}",
        "param": [
          "1.20%"
        ],
        "consume": {
          "1": [
            {
              "key": 43021023,
              "value": 3
            },
            {
              "key": 41100073,
              "value": 3
            },
            {
              "key": 2,
              "value": 50000
            }
          ]
        }
      }
    },
    "10": {
      "skill": {
        "name": "攻击提升",
        "desc": "攻击提升{0}",
        "param": [
          "1.80%"
        ],
        "consume": {
          "1": [
            {
              "key": 43021023,
              "value": 3
            },
            {
              "key": 41100073,
              "value": 3
            },
            {
              "key": 2,
              "value": 50000
            }
          ]
        }
      }
    },
    "11": {
      "skill": {
        "name": "攻击提升",
        "desc": "攻击提升{0}",
        "param": [
          "1.80%"
        ],
        "consume": {
          "1": [
            {
              "key": 43021023,
              "value": 3
            },
            {
              "key": 41100073,
              "value": 3
            },
            {
              "key": 2,
              "value": 50000
            }
          ]
        }
      }
    },
    "12": {
      "skill": {
        "name": "暴击提升",
        "desc": "暴击提升{0}",
        "param": [
          "1.20%"
        ],
        "consume": {
          "1": [
            {
              "key": 43021023,
              "value": 3
            },
            {
              "key": 41100073,
              "value": 3
            },
            {
              "key": 2,
              "value": 50000
            }
          ]
        }
      }
    },
    "13": {
      "skill": {
        "name": "暴击提升",
        "desc": "暴击提升{0}",
        "param": [
          "2.80%"
        ],
        "consume": {
          "1": [
            {
              "key": 43021024,
              "value": 3
            },
            {
              "key": 41100074,
              "value": 3
            },
            {
              "key": 41400304,
              "value": 1
            },
            {
              "key": 2,
              "value": 100000
            }
          ]
        }
      }
    },
    "14": {
      "skill": {
        "name": "攻击提升",
        "desc": "攻击提升{0}",
        "param": [
          "4.20%"
        ],
        "consume": {
          "1": [
            {
              "key": 43021024,
              "value": 3
            },
            {
              "key": 41100074,
              "value": 3
            },
            {
              "key": 41400304,
              "value": 1
            },
            {
              "key": 2,
              "value": 100000
            }
          ]
        }
      }
    },
    "15": {
      "skill": {
        "name": "攻击提升",
        "desc": "攻击提升{0}",
        "param": [
          "4.20%"
        ],
        "consume": {
          "1": [
            {
              "key": 43021024,
              "value": 3
            },
            {
              "key": 41100074,
              "value": 3
            },
            {
              "key": 41400304,
              "value": 1
            },
            {
              "key": 2,
              "value": 100000
            }
          ]
        }
      }
    },
    "16": {
      "skill": {
        "name": "暴击提升",
        "desc": "暴击提升{0}",
        "param": [
          "2.80%"
        ],
        "consume": {
          "1": [
            {
              "key": 43021024,
              "value": 3
            },
            {
              "key": 41100074,
              "value": 3
            },
            {
              "key": 41400304,
              "value": 1
            },
            {
              "key": 2,
              "value": 100000
            }
          ]
        }
      }
    },
    "17": {
      "skill": {
        "name": "骇破·熔触",
        "desc": "丽贝卡拥有为目标附加<color=Highlight>【骇破·偏移】</color>以及响应<color=Highlight>【骇破·干涉】</color>的能力。\n响应<color=Highlight>【骇破·干涉】</color>：队伍中的角色对目标造成<color=Highlight>【谐度破坏】</color>伤害并使其进入<color=Highlight>【骇破·干涉】</color>状态时，丽贝卡将施放【骇破·熔触】，同一目标每{0}秒仅可受到1次该伤害。",
        "param": [
          "8"
        ],
        "type": "谐度破坏",
        "level": {},
        "consume": {
          "1": []
        }
      }
    }
  },
  "chains": {
    "1": {
      "name": "请多指教咯~",
      "desc": "丽贝卡手枪<color=Highlight>重击</color>和霰弹<color=Highlight>普攻</color>倍率提升{0}\n丽贝卡获得<color=Highlight>小孩子才做选择！</color>效果后，额外获得{1}层街头直觉，持续{2}秒。施放<color=Highlight>战术闪避·猎手</color>、<color=Highlight>战术闪避·铁胆</color>时，若拥有街头直觉则消耗{3}层街头直觉，回复{4}点耐力。\n丽贝卡大招终结免疫打断。",
      "param": [
        "50%",
        "3",
        "12",
        "1",
        "20"
      ]
    },
    "2": {
      "name": "哦，原来是你啊！",
      "desc": "施放<color=Highlight>变奏技能</color><color=Highlight>呜呼，来发大的！</color>、<color=Highlight>变奏技能</color><color=Highlight>蠢货，有本事来抓我！</color>或<color=Highlight>共鸣解放</color>狂欢时间！时，队伍中的角色全属性伤害加成提升{0}，持续{1}秒。\n队伍中的角色附加<color=Highlight>【骇破·偏移】</color>时，全伤害加深{2}，持续{3}秒。\n处于非战斗状态时，<color=Highlight>【手感火热】</color>回复速度翻倍。",
      "param": [
        "20%",
        "30",
        "15%",
        "30"
      ]
    },
    "3": {
      "name": "背后就交给我吧！",
      "desc": "丽贝卡<color=Highlight>共鸣解放</color>狂欢时间！、<color=Highlight>共鸣解放</color><color=Highlight>大烟花！</color>伤害倍率提升{0}。\n丽贝卡<color=Highlight>共鸣解放</color>狂欢时间！爆炸范围提高。\n施放<color=Highlight>变奏技能</color><color=Highlight>呜呼，来发大的！</color>、<color=Highlight>变奏技能</color><color=Highlight>蠢货，有本事来抓我！</color>时，获得{1}点<color=Highlight>【手感火热】</color>。",
      "param": [
        "60%",
        "120"
      ]
    },
    "4": {
      "name": "我会保护你的！",
      "desc": "丽贝卡<color=Highlight>共鸣回路</color><color=Highlight>小孩子才做选择！</color>属性提升效果额外增加{0}。",
      "param": [
        "60%"
      ]
    },
    "5": {
      "name": "边缘幻梦",
      "desc": "丽贝卡施加<color=Highlight>骇破·偏移</color>时，自身普攻伤害加成提升{0}，持续{1}秒。",
      "param": [
        "20%",
        "8"
      ]
    },
    "6": {
      "name": "也许……",
      "desc": "丽贝卡从所有来源中获得的普攻伤害加成数值提升{0}。\n丽贝卡施放<color=Highlight>共鸣回路</color><color=Highlight>哒哒哒！·猎手</color>、<color=Highlight>共鸣回路</color><color=Highlight>砰砰砰！·铁胆</color>时，额外造成一次{1}的普攻伤害。\n丽贝卡<color=Highlight>共鸣回路</color><color=Highlight>哒哒哒！·猎手</color>、<color=Highlight>共鸣回路</color><color=Highlight>砰砰砰！·铁胆</color>时，额外回复{2}点<color=Highlight>【手感火热】</color>。\n处于非战斗状态大于{3}秒时，丽贝卡回复{4}点<color=Highlight>【狂热】</color>，每{5}秒只生效1次。",
      "param": [
        "50%",
        "900%",
        "20",
        "4",
        "120",
        "4"
      ]
    }
  },
  "ascensions": {
    "1": [
      {
        "key": 41100071,
        "value": 4
      },
      {
        "key": 2,
        "value": 5000
      }
    ],
    "2": [
      {
        "key": 41400314,
        "value": 3
      },
      {
        "key": 42601510,
        "value": 4
      },
      {
        "key": 41100072,
        "value": 4
      },
      {
        "key": 2,
        "value": 10000
      }
    ],
    "3": [
      {
        "key": 41400314,
        "value": 6
      },
      {
        "key": 42601510,
        "value": 8
      },
      {
        "key": 41100072,
        "value": 8
      },
      {
        "key": 2,
        "value": 15000
      }
    ],
    "4": [
      {
        "key": 41400314,
        "value": 9
      },
      {
        "key": 42601510,
        "value": 12
      },
      {
        "key": 41100073,
        "value": 4
      },
      {
        "key": 2,
        "value": 20000
      }
    ],
    "5": [
      {
        "key": 41400314,
        "value": 12
      },
      {
        "key": 42601510,
        "value": 16
      },
      {
        "key": 41100073,
        "value": 8
      },
      {
        "key": 2,
        "value": 40000
      }
    ],
    "6": [
      {
        "key": 41400314,
        "value": 16
      },
      {
        "key": 42601510,
        "value": 20
      },
      {
        "key": 41100074,
        "value": 4
      },
      {
        "key": 2,
        "value": 80000
      }
    ]
  }
}